[
  {
    "id": 9582,
    "year": 2008,
    "make": "Buick",
    "model": "Enclave",
    "type": "SUV",
    "img": "https://images.unsplash.com/photo-1621993202323-f438eec934ff?q=80&w=1964&auto=format&fit=crop&ixlib=rb-4.0.3&ixid=M3wxMjA3fDB8MHxwaG90by1wYWdlfHx8fGVufDB8fHx8fA%3D%3D",
    "description": "The Buick Enclave is a stylish and spacious SUV known for its comfortable ride and luxurious features.",
    "fuelConsumption": "10.5",
    "engineSize": "3.6L V6",
    "accessories": [
      "Leather seats",
      "Panoramic sunroof",
      "Premium audio system"
    ],
    "functionalities": [
      "Remote start",
      "Remote start",
      "Blind-spot monitoring"
    ],
    "rentalPrice": "$40",
    "rentalCompany": "Luxury",
    "address": "123 Example Street",
    "addressCity": "Kiev",
    "addressCountry": "Ukraine",
    "rentalConditions": "Minimum age: 25\nValid driver's license\nSecurity deposit required",
    "license": "Valid driver's license",
    "required": "Security deposit required",
    "mileage": 5858
  },
  {
    "id": 9584,
    "year": 2019,
    "make": "Volvo",
    "model": "XC90",
    "type": "SUV",
    "img": "https://images.unsplash.com/photo-1670362924144-7a2109885e41?q=80&w=2069&auto=format&fit=crop&ixlib=rb-4.0.3&ixid=M3wxMjA3fDB8MHxwaG90by1wYWdlfHx8fGVufDB8fHx8fA%3D%3D",
    "description": "The Volvo XC90 is a premium SUV that offers exceptional safety, advanced technology, and elegant design.",
    "fuelConsumption": "8.3",
    "engineSize": "2.0L 4-cylinder",
    "accessories": [
      "Nappa leather seats",
      "Bowers & Wilkins premium sound system",
      "Head-up display"
    ],
    "functionalities": [
      "IntelliSafe",
      "Pilot Assist semi-autonomous driving",
      "Four-zone automatic climate control"
    ],
    "rentalPrice": "$50",
    "rentalCompany": "Premium",
    "address": "456 Example Avenue",
    "addressCity": "Lviv",
    "addressCountry": "Ukraine",
    "rentalConditions": "Minimum age: 21",
    "license": "Valid driver's license",
    "required": "Proof of insurance required",
    "mileage": 5352
  },
  {
    "id": 9585,
    "year": 2023,
    "make": "BMW",
    "model": "X5",
    "type": "SUV",
    "img": "https://images.unsplash.com/photo-1701985470695-e430a8fdc8d6?q=80&w=2072&auto=format&fit=crop&ixlib=rb-4.0.3&ixid=M3wxMjA3fDB8MHxwaG90by1wYWdlfHx8fGVufDB8fHx8fA%3D%3D",
    "description": "The BMW X5 is a luxury SUV that offers a powerful engine, comfortable ride, and stylish design.",
    "fuelConsumption": "10.2",
    "engineSize": "3.0L 6-cylinder",
    "accessories": [
      "Leather seats",
      "Panoramic sunroof",
      "Heated seats"
    ],
    "functionalities": [
      "Cruise control",
      "Lane departure warning",
      "Blind spot monitoring"
    ],
    "rentalPrice": "$100",
    "rentalCompany": "Luxury",
    "address": "123 Main Street",
    "addressCity": "Kyiv",
    "addressCountry": "Ukraine",
    "rentalConditions": "Minimum age: 25",
    "license": "Valid driver's license",
    "required": "Proof of insurance required",
    "mileage": 10000
  },
  {
    "id": 9586,
    "year": 2022,
    "make": "Mercedes-Benz",
    "model": "GLE",
    "type": "SUV",
    "img": "https://images.unsplash.com/photo-1654306369985-0fb9e1a2baf5?q=80&w=2070&auto=format&fit=crop&ixlib=rb-4.0.3&ixid=M3wxMjA3fDB8MHxwaG90by1wYWdlfHx8fGVufDB8fHx8fA%3D%3D",
    "description": "The Mercedes-Benz GLE is a premium SUV that offers a luxurious interior, advanced technology, and powerful performance.",
    "fuelConsumption": "9.5",
    "engineSize": "3.0L V6",
    "accessories": [
      "Nappa leather seats",
      "Burmester sound system",
      "Airmatic suspension"
    ],
    "functionalities": [
      "Lane assist",
      "Pre-collision braking system",
      "Night vision assist"
    ],
    "rentalPrice": "$150",
    "rentalCompany": "Executive",
    "address": "567 Elm Street",
    "addressCity": "Kharkiv",
    "addressCountry": "Ukraine",
    "rentalConditions": "Minimum age: 30",
    "license": "Valid driver's license",
    "required": "Proof of insurance required",
    "mileage": 5000
  },
  {
    "id": 9587,
    "year": 2021,
    "make": "Audi",
    "model": "Q7",
    "type": "SUV",
    "img": "https://images.unsplash.com/photo-1597007030739-6d2e7172ee5b?q=80&w=2070&auto=format&fit=crop&ixlib=rb-4.0.3&ixid=M3wxMjA3fDB8MHxwaG90by1wYWdlfHx8fGVufDB8fHx8fA%3D%3D",
    "description": "The 2021 Audi Q7 is a luxury SUV that offers a spacious interior, smooth ride, and stylish design. It's perfect for those who want a comfortable and stylish ride.",
    "fuelConsumption": "8.7",
    "engineSize": "3.0L V6",
    "accessories": [
      "Leather seats",
      "Panorama sunroof",
      "Bang & Olufsen sound system"
    ],
    "functionalities": [
      "Pre Sense",
      "Audi Side Assist",
      "Audi Lane Departure Warning"
    ],
    "rentalPrice": "$200",
    "rentalCompany": "Premium",
    "address": "901 Oak Street",
    "addressCity": "Odesa",
    "addressCountry": "Ukraine",
    "rentalConditions": "Minimum age: 21",
    "license": "Valid driver's license",
    "required": "Proof of insurance required",
    "mileage": 2000
  },
  {
    "id": 9588,
    "year": 2023,
    "make": "Toyota",
    "model": "RAV4",
    "type": "SUV",
    "img": "https://images.unsplash.com/photo-1617469767053-d3b523a0b982?q=80&w=2131&auto=format&fit=crop&ixlib=rb-4.0.3&ixid=M3wxMjA3fDB8MHxwaG90by1wYWdlfHx8fGVufDB8fHx8fA%3D%3D",
    "description": "The Toyota RAV4 is a compact SUV that offers excellent fuel economy, versatile cargo space, and a comfortable ride.",
    "fuelConsumption": "7.5",
    "engineSize": "2.5L 4-cylinder",
    "accessories": [
      "Leather seats",
      "Heated front seats",
      "Sunroof"
    ],
    "functionalities": [
      "Toyota Safety",
      "Blind spot monitoring",
      "Rear cross traffic alert"
    ],
    "rentalPrice": "$45",
    "rentalCompany": "Budget",
    "address": "123 Main Street",
    "addressCity": "Kyiv",
    "addressCountry": "Ukraine",
    "rentalConditions": "Minimum age: 25",
    "license": "Valid driver's license",
    "required": "Proof of insurance required",
    "mileage": 12345
  },
  {
    "id": 9589,
    "year": 2022,
    "make": "Honda",
    "model": "CR-V",
    "type": "SUV",
    "img": "https://images.unsplash.com/photo-1609676671207-d021525a635d?q=80&w=1992&auto=format&fit=crop&ixlib=rb-4.0.3&ixid=M3wxMjA3fDB8MHxwaG90by1wYWdlfHx8fGVufDB8fHx8fA%3D%3D",
    "description": "The Honda CR-V is a midsize SUV that offers a spacious interior, a smooth ride, and a variety of engine options.",
    "fuelConsumption": "8.0",
    "engineSize": "1.5L turbocharged 4-cylinder",
    "accessories": [
      "Leather seats",
      "Panoramic sunroof",
      "Wireless charging pad"
    ],
    "functionalities": [
      "Sensing",
      "Lane departure warning",
      "Adaptive cruise control"
    ],
    "rentalPrice": "$55",
    "rentalCompany": "Enterprise",
    "address": "456 Example Avenue",
    "addressCity": "Odesa",
    "addressCountry": "Ukraine",
    "rentalConditions": "Minimum age: 21",
    "license": "Valid driver's license",
    "required": "Proof of insurance required",
    "mileage": 23456
  },
  {
    "id": 9590,
    "year": 2021,
    "make": "Hyundai",
    "model": "Tucson",
    "type": "SUV",
    "img": "https://images.unsplash.com/photo-1575090536203-2a6193126514?q=80&w=2071&auto=format&fit=crop&ixlib=rb-4.0.3&ixid=M3wxMjA3fDB8MHxwaG90by1wYWdlfHx8fGVufDB8fHx8fA%3D%3D",
    "description": "The Hyundai Tucson is a compact SUV that offers a stylish design, a comfortable ride, and a variety of features.",
    "fuelConsumption": "7.0",
    "engineSize": "2.5L 4-cylinder",
    "accessories": [
      "Heated seats",
      "Power-adjustable driver's seat",
      "Navigation system"
    ],
    "functionalities": [
      "SmartSense",
      "Blind spot monitoring",
      "Rear cross traffic alert"
    ],
    "rentalPrice": "$40",
    "rentalCompany": "Alamo",
    "address": "123 Main Street",
    "addressCity": "Kharkiv",
    "addressCountry": "Ukraine",
    "rentalConditions": "Minimum age: 21",
    "license": "Valid driver's license",
    "required": "Proof of insurance required",
    "mileage": 34567
  },
  {
    "id": 9593,
    "year": 2024,
    "make": "Buick",
    "model": "Envision",
    "type": "SUV",
    "img": "https://images.unsplash.com/photo-1684849311607-ad25cec710a7?q=80&w=1932&auto=format&fit=crop&ixlib=rb-4.0.3&ixid=M3wxMjA3fDB8MHxwaG90by1wYWdlfHx8fGVufDB8fHx8fA%3D%3D",
    "description": "The Buick Envision is a luxurious and refined SUV that offers a smooth ride, advanced technology, and spacious interior.",
    "fuelConsumption": "7.2",
    "engineSize": "2.0L turbocharged 4-cylinder",
    "accessories": [
      "Leather seats",
      "Heated and ventilated front seats",
      "Panoramic sunroof"
    ],
    "functionalities": [
      "Driver Center",
      "Lane departure warning",
      "Adaptive cruise control"
    ],
    "rentalPrice": "$60",
    "rentalCompany": "National",
    "address": "789 Oak Street",
    "addressCity": "Kyiv",
    "addressCountry": "Ukraine",
    "rentalConditions": "Minimum age: 25",
    "license": "Valid driver's license",
    "required": "Proof of insurance required",
    "mileage": 3876
  },
  {
    "id": 9594,
    "year": 2022,
    "make": "Volvo",
    "model": "S60",
    "type": "Sedan",
    "img": "https://images.unsplash.com/photo-1622594247243-749afe4cf9b9?q=80&w=1965&auto=format&fit=crop&ixlib=rb-4.0.3&ixid=M3wxMjA3fDB8MHxwaG90by1wYWdlfHx8fGVufDB8fHx8fA%3D%3D",
    "description": "The Volvo S60 is a stylish and sophisticated sedan that offers a powerful engine, advanced safety features, and a comfortable ride.",
    "fuelConsumption": "8.5",
    "engineSize": "2.0L turbocharged 4-cylinder",
    "accessories": [
      "Nappa leather interior",
      "Head-up display",
      "Harman Kardon sound system"
    ],
    "functionalities": [
      "Pilot Assist",
      "City Safety collision avoidance system",
      "Blind spot monitoring with cross traffic alert"
    ],
    "rentalPrice": "$58",
    "rentalCompany": "Hertz",
    "address": "456 Example Avenue",
    "addressCity": "Zaporizhzhia",
    "addressCountry": "Ukraine",
    "rentalConditions": "Minimum age: 23",
    "license": "Valid driver's license",
    "required": "Proof of insurance required",
    "mileage": 19234
  },
  {
    "id": 9595,
    "year": 2023,
    "make": "Hummer EV",
    "model": "Pick-up Truck",
    "type": "Electric",
    "img": "https://images.unsplash.com/photo-1578842795731-c4701423c87b?q=80&w=1935&auto=format&fit=crop&ixlib=rb-4.0.3&ixid=M3wxMjA3fDB8MHxwaG90by1wYWdlfHx8fGVufDB8fHx8fA%3D%3D",
    "description": "The Hummer EV is a revolutionary electric truck that offers exceptional off-road capability, advanced technology, and a stunning design.",
    "fuelConsumption": "0 (Electric)",
    "engineSize": "Dual electric motors",
    "accessories": [
      "Infinity surround sound system",
      "Multi-position tailgate",
      "UltraVision camera system"
    ],
    "functionalities": [
      "Super Cruise",
      "Crab Mode for tight turns",
      "Adaptive air suspension"
    ],
    "rentalPrice": "$120",
    "rentalCompany": "Turo",
    "address": "123 Main Street",
    "addressCity": "Lviv",
    "addressCountry": "Ukraine",
    "rentalConditions": "Minimum age: 25",
    "license": "Valid driver's license",
    "required": "Proof of insurance required",
    "mileage": 2765
  },
  {
    "id": 9597,
    "year": 2020,
    "make": "Mitsubishi",
    "model": "Eclipse Cross",
    "type": "SUV",
    "img": "https://images.unsplash.com/photo-1611023939376-e1e16d1c15bd?q=80&w=1974&auto=format&fit=crop&ixlib=rb-4.0.3&ixid=M3wxMjA3fDB8MHxwaG90by1wYWdlfHx8fGVufDB8fHx8fA%3D%3D",
    "description": "The Mitsubishi Eclipse Cross is a sporty and stylish SUV that offers a comfortable ride, a panoramic sunroof, and advanced driver-assistance features.",
    "fuelConsumption": "8.1",
    "engineSize": "1.5L turbocharged 4-cylinder",
    "accessories": [
      "Leather seats",
      "Panoramic sunroof",
      "Head-up display"
    ],
    "functionalities": [
      "Connect",
      "Lane departure warning",
      "Forward collision mitigation"
    ],
    "rentalPrice": "$42",
    "rentalCompany": "Dollar",
    "address": "789 Oak Street",
    "addressCity": "Odesa",
    "addressCountry": "Ukraine",
    "rentalConditions": "Minimum age: 21",
    "license": "Valid driver's license",
    "required": "Proof of insurance required",
    "mileage": 32456
  },
  {
    "id": 9598,
    "year": 2023,
    "make": "Nissan",
    "model": "Ariya",
    "type": "Electric",
    "img": "https://images.unsplash.com/photo-1589466108751-9e1daeb7ae33?q=80&w=1964&auto=format&fit=crop&ixlib=rb-4.0.3&ixid=M3wxMjA3fDB8MHxwaG90by1wYWdlfHx8fGVufDB8fHx8fA%3D%3D",
    "description": "The Nissan Ariya is a sleek and stylish electric SUV that offers long range, advanced technology, and a comfortable interior.",
    "fuelConsumption": "0 (Electric)",
    "engineSize": "Electric motor",
    "accessories": [
      "Heated and ventilated seats",
      "Panoramic sunroof",
      "Bose sound system"
    ],
    "functionalities": [
      "ProPILOT",
      "e-Pedal one-pedal driving",
      "Around View Monitor"
    ],
    "rentalPrice": "$75",
    "rentalCompany": "Avis",
    "address": "456 Example Avenue",
    "addressCity": "Ivano-Frankivsk",
    "addressCountry": "Ukraine",
    "rentalConditions": "Minimum age: 25",
    "license": "Valid driver's license",
    "required": "Proof of insurance required",
    "mileage": 4321
  },
  {
    "id": 9599,
    "year": 2019,
    "make": "Lincoln",
    "model": "Navigator",
    "type": "Luxury SUV",
    "img": "https://images.unsplash.com/photo-1671614415338-68728dd833ea?q=80&w=1974&auto=format&fit=crop&ixlib=rb-4.0.3&ixid=M3wxMjA3fDB8MHxwaG90by1wYWdlfHx8fGVufDB8fHx8fA%3D%3D",
    "description": "The Lincoln Navigator is a luxurious and spacious SUV that offers a powerful engine, advanced technology, and a variety of comfort features.",
    "fuelConsumption": "10.2",
    "engineSize": "3.5L turbocharged V6",
    "accessories": [
      "Heated and cooled seats",
      "Panoramic sunroof",
      "Revel sound system"
    ],
    "functionalities": [
      "Co-Pilot360",
      "Adaptive cruise control",
      "Blind spot monitoring with cross traffic alert"
    ],
    "rentalPrice": "$85",
    "rentalCompany": "Budget",
    "address": "123 Main Street",
    "addressCity": "Kharkiv",
    "addressCountry": "Ukraine",
    "rentalConditions": "Minimum age: 23",
    "license": "Valid driver's license",
    "required": "Proof of insurance required",
    "mileage": 28765
  },
  {
    "id": 9600,
    "year": 2023,
    "make": "GMC",
    "model": "Sierra 1500 Denali",
    "type": "Pickup Truck",
    "img": "https://images.unsplash.com/photo-1657145076873-fbee01c714db?q=80&w=2070&auto=format&fit=crop&ixlib=rb-4.0.3&ixid=M3wxMjA3fDB8MHxwaG90by1wYWdlfHx8fGVufDB8fHx8fA%3D%3D",
    "description": "The GMC Sierra 1500 Denali is a luxurious and capable pickup truck that offers a powerful V8 engine, a plush leather interior, and advanced technology features.",
    "fuelConsumption": "11.5",
    "engineSize": "5.3L V8",
    "accessories": [
      "Head-up display",
      "Surround-view camera system",
      "Bose sound system"
    ],
    "functionalities": [
      "Trailering",
      "MultiPro tailgate",
      "Adaptive cruise control"
    ],
    "rentalPrice": "$85",
    "rentalCompany": "Budget",
    "address": "567 Main Street",
    "addressCity": "Lviv",
    "addressCountry": "Ukraine",
    "rentalConditions": "Minimum age: 25",
    "license": "Valid driver's license",
    "required": "Proof of insurance required",
    "mileage": 15987
  },
  {
    "id": 9601,
    "year": 2023,
    "make": "Hyundai",
    "model": "Kona Electric",
    "type": "Electric SUV",
    "img": "https://images.unsplash.com/photo-1619767886558-efdc259cde1a?q=80&w=2071&auto=format&fit=crop&ixlib=rb-4.0.3&ixid=M3wxMjA3fDB8MHxwaG90by1wYWdlfHx8fGVufDB8fHx8fA%3D%3D",
    "description": "The Hyundai Kona Electric is a stylish and sporty electric SUV that offers an impressive range, quick acceleration, and a spacious interior.",
    "fuelConsumption": "0 (Electric)",
    "engineSize": "Electric motor",
    "accessories": [
      "Panoramic sunroof",
      "Heated and ventilated seats",
      "Wireless phone charging"
    ],
    "functionalities": [
      "Adaptive",
      "Lane keeping assist",
      "Blind spot monitoring"
    ],
    "rentalPrice": "$72",
    "rentalCompany": "Avis",
    "address": "890 Park Avenue",
    "addressCity": "Kharkiv",
    "addressCountry": "Ukraine",
    "rentalConditions": "Minimum age: 21",
    "license": "Valid driver's license",
    "required": "Proof of insurance required",
    "mileage": 10456
  },
  {
    "id": 9602,
    "year": 2023,
    "make": "Nissan",
    "model": "Frontier PRO-4X",
    "type": "Pickup Truck",
    "img": "https://images.unsplash.com/photo-1674421418135-659c44fc8b8b?q=80&w=1965&auto=format&fit=crop&ixlib=rb-4.0.3&ixid=M3wxMjA3fDB8MHxwaG90by1wYWdlfHx8fGVufDB8fHx8fA%3D%3D",
    "description": "The Nissan Frontier PRO-4X is a mid-size truck that is ready for any adventure with its off-road-tuned suspension, all-terrain tires, and electronic locking differentials.",
    "fuelConsumption": "10.8",
    "engineSize": "3.8L V6",
    "accessories": [
      "Spray-in bedliner",
      "Roof rack",
      "Tow hitch"
    ],
    "functionalities": [
      "Hill descent",
      "Off-road traction modes",
      "Rearview camera with trailer hitch assist"
    ],
    "rentalPrice": "$65",
    "rentalCompany": "Thrifty",
    "address": "123 Industrial Way",
    "addressCity": "Dnipro",
    "addressCountry": "Ukraine",
    "rentalConditions": "Minimum age: 25",
    "license": "Valid driver's license",
    "required": "Proof of insurance required",
    "mileage": 22345
  },
  {
    "id": 9604,
    "year": 2024,
    "make": "Subaru",
    "model": "Legacy Touring XT",
    "type": "Sedan",
    "img": "https://images.unsplash.com/photo-1556895534-eb15f7c16074?q=80&w=2070&auto=format&fit=crop&ixlib=rb-4.0.3&ixid=M3wxMjA3fDB8MHxwaG90by1wYWdlfHx8fGVufDB8fHx8fA%3D%3D",
    "description": "The Subaru Legacy Touring XT is a stylish and capable sedan that offers a powerful turbocharged engine, all-wheel drive, and a comfortable ride.",
    "fuelConsumption": "8.8",
    "engineSize": "2.5L turbocharged 4-cylinder",
    "accessories": [
      "Leather-trimmed seats",
      "Heated steering wheel",
      "Sunroof"
    ],
    "functionalities": [
      "EyeSight",
      "Dual-zone automatic climate control",
      "Power moonroof"
    ],
    "rentalPrice": "$60",
    "rentalCompany": "Sixt",
    "address": "345 Maple Street",
    "addressCity": "Kyiv",
    "addressCountry": "Ukraine",
    "rentalConditions": "Minimum age: 23",
    "license": "Valid driver's license",
    "required": "Proof of insurance required",
    "mileage": 8765
  },
  {
    "id": 9605,
    "year": 2023,
    "make": "Mitsubishi Eclipse Cross GT",
    "type": "SUV",
    "img": "https://images.unsplash.com/photo-1651446404130-104e68e2f39a?q=80&w=1932&auto=format&fit=crop&ixlib=rb-4.0.3&ixid=M3wxMjA3fDB8MHxwaG90by1wYWdlfHx8fGVufDB8fHx8fA%3D%3D",
    "description": "The Mitsubishi Eclipse Cross GT is a sporty and stylish SUV that offers a panoramic sunroof, advanced driver-assistance features, and a comfortable interior.",
    "fuelConsumption": "8.3",
    "engineSize": "1.5L turbocharged 4-cylinder",
    "accessories": [
      "Panoramic sunroof",
      "Head-up display",
      "Bose sound system"
    ],
    "functionalities": [
      "Connect",
      "Lane departure warning",
      "Forward collision mitigation"
    ],
    "rentalPrice": "$48",
    "rentalCompany": "Hertz",
    "address": "789 Oak Street",
    "addressCity": "Odesa",
    "addressCountry": "Ukraine",
    "rentalConditions": "Minimum age: 21",
    "license": "Valid driver's license",
    "required": "Proof of insurance required",
    "mileage": 19234
  },
  {
    "id": 9606,
    "year": 2022,
    "make": "Nissan",
    "type": "SUV",
    "img": "https://images.unsplash.com/photo-1494697536454-6f39e2cc972d?q=80&w=2071&auto=format&fit=crop&ixlib=rb-4.0.3&ixid=M3wxMjA3fDB8MHxwaG90by1wYWdlfHx8fGVufDB8fHx8fA%3D%3D",
    "description": "The Nissan Pathfinder Rock Creek is a rugged and adventurous SUV that offers excellent off-road capability, advanced technology, and a spacious interior.",
    "fuelConsumption": "9.2",
    "engineSize": "3.5L V6",
    "accessories": [
      "Roof rails",
      "All-terrain tires",
      "Tow hitch"
    ],
    "functionalities": [
      "ProPILOT",
      "Surround-view camera system",
      "Off-road driving modes"
    ],
    "rentalPrice": "$78",
    "rentalCompany": "Dollar",
    "address": "456 Example Avenue",
    "addressCity": "Ivano-Frankivsk",
    "addressCountry": "Ukraine",
    "rentalConditions": "Minimum age: 25",
    "license": "Valid driver's license",
    "required": "Proof of insurance required",
    "mileage": 24567
  },
  {
    "id": 9608,
    "year": 2024,
    "make": "GMC Sierra 1500 AT4",
    "type": "Pickup Truck",
    "img": "https://images.unsplash.com/photo-1572834071769-59f8e8a6b2dd?q=80&w=1962&auto=format&fit=crop&ixlib=rb-4.0.3&ixid=M3wxMjA3fDB8MHxwaG90by1wYWdlfHx8fGVufDB8fHx8fA%3D%3D",
    "description": "The GMC Sierra 1500 AT4 is a rugged and capable pickup truck that's ready for any adventure with its off-road-tuned suspension, all-terrain tires, and advanced driver-assistance features.",
    "fuelConsumption": "11.8",
    "engineSize": "5.3L V8",
    "accessories": [
      "Bedliner",
      "Off-road lights",
      "GoPro Mount"
    ],
    "functionalities": [
      "Hill descent",
      "Traction control system",
      "Trailer sway control"
    ],
    "rentalPrice": "$88",
    "rentalCompany": "Enterprise",
    "address": "123 Elm Street",
    "addressCity": "Zaporizhzhia",
    "addressCountry": "Ukraine",
    "rentalConditions": "Minimum age: 25",
    "license": "Valid driver's license",
    "required": "Proof of insurance required",
    "mileage": 12345
  },
  {
    "id": 9609,
    "year": 2023,
    "make": "Hyundai",
    "type": "SUV",
    "img": "https://images.unsplash.com/photo-1645492708376-155f3bc23fc4?q=80&w=2071&auto=format&fit=crop&ixlib=rb-4.0.3&ixid=M3wxMjA3fDB8MHxwaG90by1wYWdlfHx8fGVufDB8fHx8fA%3D%3D",
    "description": "The Hyundai Palisade Calligraphy is a luxurious and spacious SUV that offers a powerful engine, advanced technology, and a comfortable interior for the whole family.",
    "fuelConsumption": "9.5",
    "engineSize": "3.8L V6",
    "accessories": [
      "Nappa leather interior",
      "Panoramic sunroof",
      "Heads-up display"
    ],
    "functionalities": [
      "Driving assist",
      "Blind spot detection",
      "Surround-view camera system"
    ],
    "rentalPrice": "$92",
    "rentalCompany": "Alamo",
    "address": "789 Oak Street",
    "addressCity": "Lviv",
    "addressCountry": "Ukraine",
    "rentalConditions": "Minimum age: 23",
    "license": "Valid driver's license",
    "required": "Proof of insurance required",
    "mileage": 8901
  },
  {
    "id": 9610,
    "year": 2022,
    "make": "Nissan Ariya Premiere",
    "type": "Electric SUV",
    "img": "https://images.unsplash.com/photo-1642004614576-877e9266828a?q=80&w=2070&auto=format&fit=crop&ixlib=rb-4.0.3&ixid=M3wxMjA3fDB8MHxwaG90by1wYWdlfHx8fGVufDB8fHx8fA%3D%3D",
    "description": "The Nissan Ariya Premiere is a sleek and stylish electric SUV that offers long range, advanced technology, and a comfortable interior for a futuristic driving experience.",
    "fuelConsumption": "0 (Electric)",
    "engineSize": "Electric motor",
    "accessories": [
      "Bose premium audio system",
      "Heated and ventilated seats",
      "Tri-zone automatic climate control"
    ],
    "functionalities": [
      "ProPILOT",
      "e-Pedal one-pedal driving",
      "Around View Monitor"
    ],
    "rentalPrice": "$80",
    "rentalCompany": "National",
    "address": "456 Example Avenue",
    "addressCity": "Kharkiv",
    "addressCountry": "Ukraine",
    "rentalConditions": "Minimum age: 25",
    "license": "Valid driver's license",
    "required": "Proof of insurance required",
    "mileage": 15678
  },
  {
    "id": 9612,
    "year": 2024,
    "make": "GMC Canyon AT4",
    "type": "Mid-size Truck",
    "img": "https://images.unsplash.com/photo-1577496550332-559de2472874?q=80&w=2074&auto=format&fit=crop&ixlib=rb-4.0.3&ixid=M3wxMjA3fDB8MHxwaG90by1wYWdlfHx8fGVufDB8fHx8fA%3D%3D",
    "description": "The GMC Canyon AT4 is a capable and versatile mid-size truck that conquers any adventure with its off-road prowess, advanced technology, and comfortable interior.",
    "fuelConsumption": "10.5",
    "engineSize": "3.6L V6",
    "accessories": [
      "Bed cover",
      "Off-road tires",
      "Hitch mounted bike rack"
    ],
    "functionalities": [
      "Descent control",
      "Off-road cruise control",
      "Bose premium audio system"
    ],
    "rentalPrice": "$62",
    "rentalCompany": "Budget",
    "address": "345 Maple Street",
    "addressCity": "Kyiv",
    "addressCountry": "Ukraine",
    "rentalConditions": "Minimum age: 23",
    "license": "Valid driver's license",
    "required": "Proof of insurance required",
    "mileage": 18765
  },
  {
    "id": 9613,
    "year": 2023,
    "make": "Hyundai",
    "type": "SUV",
    "img": "https://images.unsplash.com/photo-1646728502468-06d9c7b3c2c2?q=80&w=2070&auto=format&fit=crop&ixlib=rb-4.0.3&ixid=M3wxMjA3fDB8MHxwaG90by1wYWdlfHx8fGVufDB8fHx8fA%3D%3D",
    "description": "The Hyundai Santa Fe Calligraphy is a luxurious and spacious SUV that offers a powerful engine, advanced technology, and a comfortable interior for the whole family.",
    "fuelConsumption": "9.1",
    "engineSize": "2.5L turbocharged 4-cylinder",
    "accessories": [
      "Nappa leather upholstery",
      "Heated and ventilated seats",
      "Panoramic sunroof"
    ],
    "functionalities": [
      "Driving assist",
      "Blind spot detection",
      "Surround-view camera system"
    ],
    "rentalPrice": "$85",
    "rentalCompany": "Alamo",
    "address": "123 Elm Street",
    "addressCity": "Zaporizhzhia",
    "addressCountry": "Ukraine",
    "rentalConditions": "Minimum age: 21",
    "license": "Valid driver's license",
    "required": "Proof of insurance required",
    "mileage": 10234
  },
  {
    "id": 9614,
    "year": 2022,
    "make": "Nissan Leaf PLUS",
    "type": "Electric Hatchback",
    "img": "https://images.unsplash.com/photo-1618091171668-e1c3cf1ffce2?q=80&w=1964&auto=format&fit=crop&ixlib=rb-4.0.3&ixid=M3wxMjA3fDB8MHxwaG90by1wYWdlfHx8fGVufDB8fHx8fA%3D%3D",
    "description": "The Nissan Leaf PLUS is a practical and efficient electric hatchback that offers long range, advanced technology, and a spacious interior for everyday driving.",
    "fuelConsumption": "0 (Electric)",
    "engineSize": "Electric motor",
    "accessories": [
      "Bose premium audio system",
      "Heated seats",
      "Apple CarPlay and Android Auto compatibility"
    ],
    "functionalities": [
      "ProPILOT",
      "e-Pedal one-pedal driving",
      "Parking sensors"
    ],
    "rentalPrice": "$55",
    "rentalCompany": "National",
    "address": "789 Oak Street",
    "addressCity": "Lviv",
    "addressCountry": "Ukraine",
    "rentalConditions": "Minimum age: 21",
    "license": "Valid driver's license",
    "required": "Proof of insurance required",
    "mileage": 23456
  },
  {
    "id": 9616,
    "year": 2024,
    "make": "Buick Enclave Avenir",
    "type": "Luxury SUV",
    "img": "https://images.unsplash.com/photo-1684849311607-ad25cec710a7?q=80&w=1932&auto=format&fit=crop&ixlib=rb-4.0.3&ixid=M3wxMjA3fDB8MHxwaG90by1wYWdlfHx8fGVufDB8fHx8fA%3D%3D",
    "description": "This luxurious and spacious SUV boasts a powerful engine, cutting-edge technology, and top-notch materials for a truly refined driving experience.",
    "fuelConsumption": "10.8",
    "engineSize": "3.6L V6",
    "accessories": [
      "Heated and cooled Nappa leather seats",
      "Head-up display",
      "Bose premium audio system"
    ],
    "functionalities": [
      "Super Cruise",
      "Enhanced vision night camera",
      "Blind spot monitoring with cross traffic alert"
    ],
    "rentalPrice": "$95",
    "rentalCompany": "Hertz",
    "address": "456 Example Avenue",
    "addressCity": "Kharkiv",
    "addressCountry": "Ukraine",
    "rentalConditions": "Minimum age: 25",
    "license": "Valid driver's license",
    "required": "Proof of insurance required",
    "mileage": 5678
  },
  {
    "id": 9617,
    "year": 2023,
    "make": "Volvo XC40",
    "type": "Electric SUV",
    "img": "https://images.unsplash.com/photo-1633102072414-cd078e898307?q=80&w=2070&auto=format&fit=crop&ixlib=rb-4.0.3&ixid=M3wxMjA3fDB8MHxwaG90by1wYWdlfHx8fGVufDB8fHx8fA%3D%3D",
    "description": "This sleek and stylish electric SUV combines impressive range, performance, and safety features to offer a thrilling and eco-conscious driving experience.",
    "fuelConsumption": "0 (Electric)",
    "engineSize": "Dual electric motors",
    "accessories": [
      "Panoramic sunroof",
      "Pixel LED headlights",
      "Harman Kardon sound system"
    ],
    "functionalities": [
      "Assist driving",
      "City Safety collision avoidance system",
      "360-degree surround view camera"
    ],
    "rentalPrice": "$82",
    "rentalCompany": "Avis",
    "address": "789 Oak Street",
    "addressCity": "Odesa",
    "addressCountry": "Ukraine",
    "rentalConditions": "Minimum age: 23",
    "license": "Valid driver's license",
    "required": "Proof of insurance required",
    "mileage": 12345
  },
  {
    "id": 9618,
    "year": 2023,
    "make": "Hummer EV SUV Edition 1",
    "type": "Electric SUV",
    "img": "https://images.unsplash.com/photo-1694059812161-a36a20c14c5b?q=80&w=2060&auto=format&fit=crop&ixlib=rb-4.0.3&ixid=M3wxMjA3fDB8MHxwaG90by1wYWdlfHx8fGVufDB8fHx8fA%3D%3D",
    "description": "This futuristic electric SUV pushes boundaries with its off-road prowess, innovative technology, and luxurious interior, making it ideal for the adventurous driver seeking ultimate performance.",
    "fuelConsumption": "0 (Electric)",
    "engineSize": "Triple electric motors",
    "accessories": [
      "Infinity roof with removable panels",
      "Crab Mode diagonal driving",
      "UltraVision camera system with underbody cameras"
    ],
    "functionalities": [
      "Super Cruise",
      "Adaptive cruise control",
      "Surround-view camera system with trailer view"
    ],
    "rentalPrice": "$120",
    "rentalCompany": "Enterprise",
    "address": "123 Elm Street",
    "addressCity": "Zaporizhzhia",
    "addressCountry": "Ukraine",
    "rentalConditions": "Minimum age: 25",
    "license": "Valid driver's license",
    "required": "Proof of insurance required",
    "mileage": 3456
  },
  {
    "id": 9620,
    "year": 2023,
    "make": "Toyota RAV4 Prime XSE",
    "type": "SUV",
    "img": "https://images.unsplash.com/photo-1617469767053-d3b523a0b982?q=80&w=2131&auto=format&fit=crop&ixlib=rb-4.0.3&ixid=M3wxMjA3fDB8MHxwaG90by1wYWdlfHx8fGVufDB8fHx8fA%3D%3D",
    "description": "This sporty and efficient plug-in hybrid SUV offers a blend of performance, fuel efficiency, and all-wheel drive capability, making it a versatile choice for daily commutes and weekend adventures.",
    "fuelConsumption": "6.5 (Combined)",
    "engineSize": "2.5L 4-cylinder + electric motor",
    "accessories": [
      "Panoramic sunroof",
      "JBL premium audio system",
      "Heated and ventilated front seats"
    ],
    "functionalities": [
      "Sense 2.5+",
      "Apple CarPlay and Android Auto compatibility",
      "Wireless charging pad"
    ],
    "rentalPrice": "$76",
    "rentalCompany": "Sixt",
    "address": "345 Maple Street",
    "addressCity": "Kyiv",
    "addressCountry": "Ukraine",
    "rentalConditions": "Minimum age: 23",
    "license": "Valid driver's license",
    "required": "Proof of insurance required",
    "mileage": 15678
  },
  {
    "id": 9621,
    "year": 2024,
    "make": "Chevrolet Silverado ZR2",
    "type": "Pickup Truck",
    "img": "https://images.unsplash.com/photo-1590510616176-67c37c34fa28?q=80&w=2070&auto=format&fit=crop&ixlib=rb-4.0.3&ixid=M3wxMjA3fDB8MHxwaG90by1wYWdlfHx8fGVufDB8fHx8fA%3D%3D",
    "description": "This capable and rugged pickup truck conquers any terrain with its off-road suspension, powerful engine, and advanced features, making it ideal for those who demand serious performance and capability.",
    "fuelConsumption": "13.2",
    "engineSize": "6.2L V8",
    "accessories": [
      "Multimatic DSSV spool-valve shocks",
      "E-Lockers front and rear differentials",
      "Rock sliders"
    ],
    "functionalities": [
      "Trailering",
      "Hill descent control",
      "360-degree surround view camera system"
    ],
    "rentalPrice": "$105",
    "rentalCompany": "Budget",
    "address": "123 Elm Street",
    "addressCity": "Zaporizhzhia",
    "addressCountry": "Ukraine",
    "rentalConditions": "Minimum age: 25",
    "license": "Valid driver's license",
    "required": "Proof of insurance required",
    "mileage": 9876
  },
  {
    "id": 9622,
    "year": 2023,
    "make": "Honda",
    "type": "Sedan",
    "img": "https://images.unsplash.com/photo-1634737581963-5a22ba471961?q=80&w=2143&auto=format&fit=crop&ixlib=rb-4.0.3&ixid=M3wxMjA3fDB8MHxwaG90by1wYWdlfHx8fGVufDB8fHx8fA%3D%3D",
    "description": "This elegant and efficient sedan combines comfort, performance, and fuel economy for a refined and eco-friendly driving experience.",
    "fuelConsumption": "5.4 (Combined)",
    "engineSize": "2.0L 4-cylinder + electric motor",
    "accessories": [
      "Head-up display",
      "Heated and ventilated leather seats",
      "Wireless Apple CarPlay and Android Auto"
    ],
    "functionalities": [
      "Sensing",
      "Adaptive cruise control with low-speed follow",
      "Lane keeping assist"
    ],
    "rentalPrice": "$68",
    "rentalCompany": "Thrifty",
    "address": "789 Oak Street",
    "addressCity": "Lviv",
    "addressCountry": "Ukraine",
    "rentalConditions": "Minimum age: 21",
    "license": "Valid driver's license",
    "required": "Proof of insurance required",
    "mileage": 21098
  },
  {
    "id": 9624,
    "year": 2023,
    "make": "Kia EV6 GT-Line",
    "type": "Crossover",
    "img": "https://images.unsplash.com/photo-1655945601270-17b34b82a9de?q=80&w=2070&auto=format&fit=crop&ixlib=rb-4.0.3&ixid=M3wxMjA3fDB8MHxwaG90by1wYWdlfHx8fGVufDB8fHx8fA%3D%3D",
    "description": "This stylish and high-tech electric crossover offers impressive range, performance, and a spacious, comfortable interior, making it a compelling choice for eco-conscious drivers seeking a modern and engaging driving experience.",
    "fuelConsumption": "0 (Electric)",
    "engineSize": "Electric motor",
    "accessories": [
      "Dual panoramic curved display",
      "Augmented reality head-up display",
      "Meridian premium sound system"
    ],
    "functionalities": [
      "Assist 2",
      "Remote Smart Parking Assist",
      "Surround View Monitor"
    ],
    "rentalPrice": "$79",
    "rentalCompany": "Avis",
    "address": "456 Example Avenue",
    "addressCity": "Kharkiv",
    "addressCountry": "Ukraine",
    "rentalConditions": "Minimum age: 23",
    "license": "Valid driver's license",
    "required": "Proof of insurance required",
    "mileage": 18765
  },
  {
    "id": 9625,
    "year": 2024,
    "make": "Audi e-tron S Sportback",
    "type": "Electric SUV",
    "img": "https://images.unsplash.com/photo-1614328467603-0444b9fcfc47?q=80&w=2070&auto=format&fit=crop&ixlib=rb-4.0.3&ixid=M3wxMjA3fDB8MHxwaG90by1wYWdlfHx8fGVufDB8fHx8fA%3D%3D",
    "description": "This luxurious and high-performance electric SUV delivers exhilarating acceleration, precise handling, and a sleek, sophisticated design, making it a top choice for drivers seeking a blend of luxury and excitement.",
    "fuelConsumption": "0 (Electric)",
    "engineSize": "Dual electric motors",
    "accessories": [
      "Virtual cockpit plus",
      "Bang & Olufsen 3D sound system",
      "Head-up display"
    ],
    "functionalities": [
      "Audi adaptive",
      "Audi pre sense front with pedestrian detection",
      "360-degree surround view cameras"
    ],
    "rentalPrice": "$110",
    "rentalCompany": "Hertz",
    "address": "789 Oak Street",
    "addressCity": "Odesa",
    "addressCountry": "Ukraine",
    "rentalConditions": "Minimum age: 25",
    "license": "Valid driver's license",
    "required": "Proof of insurance required",
    "mileage": 10234
  },
  {
    "id": 9626,
    "year": 2023,
    "make": "Jeep Wrangler 4xe Rubicon",
    "type": "SUV",
    "img": "https://images.unsplash.com/photo-1486496572940-2bb2341fdbdf?q=80&w=2070&auto=format&fit=crop&ixlib=rb-4.0.3&ixid=M3wxMjA3fDB8MHxwaG90by1wYWdlfHx8fGVufDB8fHx8fA%3D%3D",
    "description": "This iconic off-roader combines the legendary capability of the Wrangler with the efficiency and eco-friendliness of a plug-in hybrid powertrain, allowing for open-air adventures with reduced emissions.",
    "fuelConsumption": "4.7 (Combined)",
    "engineSize": "2.0L 4-cylinder + electric motor",
    "accessories": [
      "Trail rated badge",
      "Rock rails",
      "Removable hardtop"
    ],
    "functionalities": [
      "4x4 powertrain",
      "Front and rear locking differentials",
      "360-degree surround view camera system"
    ],
    "rentalPrice": "$98",
    "rentalCompany": "Sixt",
    "address": "345 Maple Street",
    "addressCity": "Kyiv",
    "addressCountry": "Ukraine",
    "rentalConditions": "Minimum age: 25",
    "license": "Valid driver's license",
    "required": "Proof of insurance required",
    "mileage": 14567
  }
]